chromoscope/__about__.py
chromoscope/__init__.py
chromoscope/_viewer.py
chromoscope-0.0.3.dist-info/METADATA
chromoscope-0.0.3.dist-info/WHEEL
chromoscope-0.0.3.dist-info/RECORD
