Metadata-Version: 2.1
Name: chromoscope
Version: 0.0.3
Project-URL: Documentation, https://github.com/hms-dbmi/chromoscope#readme
Project-URL: Issues, https://github.com/hms-dbmi/chromoscope/issues
Project-URL: Source, https://github.com/hms-dbmi/chromoscope
Author-email: Sehi L'Yi <sehi_lyi@hms.harvard.edu>, Trevor Manz <trevor.j.manz@gmail.com>
License-Expression: MIT
Classifier: Development Status :: 4 - Beta
Classifier: Programming Language :: Python
Classifier: Programming Language :: Python :: 3.7
Classifier: Programming Language :: Python :: 3.8
Classifier: Programming Language :: Python :: 3.9
Classifier: Programming Language :: Python :: 3.10
Classifier: Programming Language :: Python :: 3.11
Classifier: Programming Language :: Python :: Implementation :: CPython
Classifier: Programming Language :: Python :: Implementation :: PyPy
Requires-Python: >=3.7
Requires-Dist: jinja2
Requires-Dist: servir>=0.0.5
